{"api_api.md":"DsjikoNI","api_diagnostics.md":"WKIIuAhc","configuration.md":"Dejiywnf","crtdl_consent-key.md":"cl0OepkV","crtdl_crtdl.md":"BFWlIUAg","crtdl_filter.md":"Cadph4a9","documentation.md":"BvBiJAQN","getting-started.md":"5KHlbmtu","implementation_cascading-delete.md":"BaYPoEp4","implementation_consent.md":"DBWcSTay","implementation_data-extraction.md":"vyRJFv45","implementation_direct-load.md":"DfYe8mxb","implementation_error-codes.md":"SRM2DtZI","implementation_implementation-overview.md":"BENzVaPI","implementation_limitations.md":"Dlbp3gMe","implementation_must-have.md":"C33L3LoE","implementation_provenance.md":"D6mcolyh","implementation_redaction.md":"xQ_0n42U","implementation_reference-resolve.md":"-Rb45H2J","implementation_validation.md":"CakLyjID","index.md":"BB_UCq1e","overview.md":"_5elrd1y"}
