{"api_api.md":"DGGTr1bh","api_diagnostics.md":"BXJzLHqw","configuration.md":"zNanwpFt","crtdl_consent-key.md":"Cn6ujMwF","crtdl_crtdl.md":"PcgMAJ4d","crtdl_filter.md":"CnFRBXEI","documentation.md":"Gbxd59Nu","getting-started.md":"B4H4a-cV","implementation_cascading-delete.md":"DHJopkuz","implementation_consent.md":"9R1N0o69","implementation_data-extraction.md":"DZJ-MZ6J","implementation_direct-load.md":"BEid5wwq","implementation_error-codes.md":"DlmrVTpO","implementation_implementation-overview.md":"DG2NK7R9","implementation_limitations.md":"InXvTEU3","implementation_must-have.md":"CMejzDFR","implementation_provenance.md":"D282lyGa","implementation_redaction.md":"Cg9Ty0jT","implementation_reference-resolve.md":"fwWNLRRm","implementation_validation.md":"CdViIlvv","index.md":"DASEhE-W","overview.md":"CcICKDgR"}
