{"api_api.md":"DCkwnwR6","api_diagnostics.md":"CSYkC2P4","configuration.md":"DxtVWWsu","crtdl_consent-key.md":"DdbgkvhB","crtdl_crtdl.md":"D5nNABNL","crtdl_filter.md":"DCb8S8AP","documentation.md":"CsHT2pmi","getting-started.md":"DwIgpmXz","implementation_cascading-delete.md":"AHs3HwL-","implementation_consent.md":"DsVlhQ7C","implementation_data-extraction.md":"GmnEZSfJ","implementation_direct-load.md":"CFb4NnwH","implementation_error-codes.md":"C7ZLPGDj","implementation_implementation-overview.md":"BNK4sG-r","implementation_limitations.md":"D1pNYWHo","implementation_must-have.md":"C1qjHXck","implementation_provenance.md":"DLtPE2ce","implementation_redaction.md":"CFAqzK-n","implementation_reference-resolve.md":"DvgqMMOe","implementation_validation.md":"ClaZkZmm","index.md":"KWIh32pV","overview.md":"8FFTyRkm"}
